MANIFEST.in
requirements.txt
setup.py
fdt_sqlalchemy.egg-info/PKG-INFO
fdt_sqlalchemy.egg-info/SOURCES.txt
fdt_sqlalchemy.egg-info/dependency_links.txt
fdt_sqlalchemy.egg-info/not-zip-safe
fdt_sqlalchemy.egg-info/requires.txt
fdt_sqlalchemy.egg-info/top_level.txt
fdtsqlalchemy/__init__.py
fdtsqlalchemy/templates/explain.html
fdtsqlalchemy/templates/select.html
fdtsqlalchemy/templates/sqla.html