Metadata-Version: 1.1
Name: fdt-sqlalchemy
Version: 0.0.1
Summary: Flask-debugtoolbar configurable SQLAlchemy panel
Home-page: https://github.com/clavery/fdt-sqlalchemy
Author: Charles Lavery
Author-email: charles.lavery@gmail.com
License: BSD
Platform: UNKNOWN
Classifier: Development Status :: 3 - Alpha
Classifier: Intended Audience :: Developers
Classifier: Natural Language :: English
Classifier: License :: OSI Approved :: MIT License
Classifier: Programming Language :: Python
Classifier: Programming Language :: Python :: 2.6
Classifier: Programming Language :: Python :: 2.7
